python_blame/__init__.py
python_blame-0.1.3.dist-info/entry_points.txt
python_blame-0.1.3.dist-info/LICENSE
python_blame-0.1.3.dist-info/WHEEL
python_blame-0.1.3.dist-info/METADATA
python_blame-0.1.3.dist-info/RECORD
