Metadata-Version: 2.1
Name: python-blame
Version: 0.1.3
Summary: A Python tool and a library for blaming Python code
Home-page: UNKNOWN
License: Apache-2.0
Author: Roman Inflianskas
Author-email: infroma@gmail.com
Requires-Python: >=3.5,<4.0
Classifier: License :: OSI Approved :: Apache Software License
Classifier: Programming Language :: Python :: 3
Classifier: Programming Language :: Python :: 3.5
Classifier: Programming Language :: Python :: 3.6
Classifier: Programming Language :: Python :: 3.7
Requires-Dist: astroid (>=2.2,<3.0)
Requires-Dist: docopt (>=0.6.2,<0.7.0)
Requires-Dist: plumbum (>=1.6,<2.0)
Requires-Dist: poetry-version (>=0.1.3,<0.2.0)
Requires-Dist: ruamel.yaml (>=0.15.89,<0.16.0)
